{"name":"Theonia","id":"u0faMlW73WOB5pIP","time":1689062738804,"cities":{"7_3.city":{"locked":true,"created":false},"8_0.city":{"locked":true,"created":false},"6_3.city":{"locked":true,"created":false},"8_3.city":{"locked":true,"created":false},"8_6.city":{"locked":true,"created":false},"6_6.city":{"locked":true,"created":false},"4_6.city":{"locked":true,"created":false},"10_2.city":{"locked":true,"created":false},"4_4.city":{"locked":true,"created":false},"0_4.city":{"locked":true,"created":false},"4_0.city":{"locked":true,"created":false},"9_3.city":{"locked":true,"created":false},"6_0.city":{"locked":true,"created":false},"10_6.city":{"locked":true,"created":false},"0_0.city":{"locked":true,"created":false},"4_2.city":{"locked":true,"created":false},"8_4.city":{"locked":true,"created":false},"6_2.city":{"locked":true,"created":false},"10_0.city":{"locked":true,"created":false},"6_4.city":{"locked":true,"created":false},"9_4.city":{"locked":true,"created":false},"7_4.city":{"locked":false,"created":true,"sign":"N180LmNpdHl1MGZhTWxXNzNXT0I1cElQ"},"9_5.city":{"locked":true,"created":false},"8_8.city":{"locked":true,"created":false},"9_2.city":{"locked":true,"created":false},"10_4.city":{"locked":true,"created":false},"8_5.city":{"locked":true,"created":false},"7_5.city":{"locked":true,"created":false},"8_2.city":{"locked":true,"created":false},"7_2.city":{"locked":true,"created":false},"6_5.city":{"locked":true,"created":false},"0_8.city":{"locked":true,"created":false},"4_8.city":{"locked":true,"created":false}}}